fields_metadata/__init__.py
fields_metadata/annotations.py
fields_metadata/exceptions.py
fields_metadata/extractor.py
fields_metadata/metadata.py
fields_metadata/path.py
fields_metadata/py.typed
fields_metadata/type_utils.py
fields_metadata-1.4.1.dist-info/METADATA
fields_metadata-1.4.1.dist-info/WHEEL
fields_metadata-1.4.1.dist-info/licenses/LICENSE
fields_metadata-1.4.1.dist-info/RECORD
