Metadata-Version: 2.4
Name: fields-metadata
Version: 1.4.1
Summary: A Python library for extracting field metadata from dataclasses and Pydantic models
Project-URL: Homepage, https://github.com/Kencho1/fields-metadata
Project-URL: Repository, https://github.com/Kencho1/fields-metadata
Author: Jesús Alonso Abad
License: MIT
License-File: LICENSE
Keywords: dataclass,introspection,metadata,pydantic,reflection
Classifier: Development Status :: 5 - Production/Stable
Classifier: Intended Audience :: Developers
Classifier: License :: OSI Approved :: MIT License
Classifier: Programming Language :: Python :: 3
Classifier: Programming Language :: Python :: 3.11
Classifier: Programming Language :: Python :: 3.12
Classifier: Programming Language :: Python :: 3.13
Classifier: Programming Language :: Python :: 3.14
Classifier: Typing :: Typed
Requires-Python: >=3.11
Requires-Dist: annotated-types~=0.6
Provides-Extra: dev
Requires-Dist: mypy>=1.7.0; extra == 'dev'
Requires-Dist: pytest-cov>=4.1.0; extra == 'dev'
Requires-Dist: pytest>=7.4.0; extra == 'dev'
Requires-Dist: ruff>=0.1.0; extra == 'dev'
Requires-Dist: tox>=4.0.0; extra == 'dev'
Provides-Extra: pydantic
Requires-Dist: pydantic>=2.0; extra == 'pydantic'
